{
  "collectionName": "components_images_img_urls",
  "info": {
    "name": "imgUrls",
    "icon": "images",
    "description": ""
  },
  "options": {},
  "attributes": {
    "featured": {
      "type": "boolean",
      "default": false
    },
    "mediaType": {
      "type": "enumeration",
      "enum": [
        "photo",
        "video"
      ],
      "required": true,
      "default": "photo"
    },
    "mediaUrl": {
      "model": "file",
      "via": "related",
      "allowedTypes": [
        "files",
        "images",
        "videos"
      ],
      "plugin": "upload",
      "required": true
    }
  }
}
